topsisx/__init__.py
topsisx/__main__.py
topsisx/cli.py
topsisx/core.py
topsisx/py.typed
topsisx_arpit_102203499-0.1.0.dist-info/METADATA
topsisx_arpit_102203499-0.1.0.dist-info/WHEEL
topsisx_arpit_102203499-0.1.0.dist-info/entry_points.txt
topsisx_arpit_102203499-0.1.0.dist-info/licenses/LICENSE
topsisx_arpit_102203499-0.1.0.dist-info/licenses/LICENSE.txt
topsisx_arpit_102203499-0.1.0.dist-info/RECORD
