Metadata-Version: 2.4
Name: topsisx-arpit-102203499
Version: 0.1.0
Summary: A simple, typed TOPSIS implementation with a CLI.
Project-URL: Homepage, https://github.com/jarpit2003/topsisx
Project-URL: Repository, https://github.com/jarpit2003/topsisx
Author: Arpit Jain
License: MIT License
License-File: LICENSE
License-File: LICENSE.txt
Keywords: decision-making,mcdm,topsis
Requires-Python: >=3.9
Requires-Dist: numpy>=1.22
Requires-Dist: pandas>=1.5
